technicolorgateway/__init__.py
technicolorgateway/modal.py
technicolorgateway/mysrp.py
pytechnicolor-1.1.12.dist-info/METADATA
pytechnicolor-1.1.12.dist-info/WHEEL
pytechnicolor-1.1.12.dist-info/top_level.txt
pytechnicolor-1.1.12.dist-info/RECORD
