Metadata-Version: 2.1
Name: pytechnicolor
Version: 1.1.12
Summary: Technicolor Gateway library
Home-page: https://github.com/shaiu/techicolorgateway
Author: Shai Ungar
Author-email: shaiungar@gmail.com
License: MIT
Classifier: License :: OSI Approved :: MIT License
Classifier: Programming Language :: Python :: 3
Classifier: Programming Language :: Python :: 3.7
Requires-Dist: six
Requires-Dist: html2text
Requires-Dist: robobrowser
Requires-Dist: Werkzeug (==0.16.1)
